math_for_cannibals/RightTriangle.py
math_for_cannibals/__init__.py
math_for_cannibals-2.dist-info/LICENSE.txt
math_for_cannibals-2.dist-info/METADATA
math_for_cannibals-2.dist-info/WHEEL
math_for_cannibals-2.dist-info/top_level.txt
math_for_cannibals-2.dist-info/RECORD
