Metadata-Version: 2.1
Name: math-for-cannibals
Version: 2
Summary: Math functions to simplify mathematical tasks
Home-page: https://gitlab.com/hann1ba1/math-for-cannibals
Author: Hannibal Lykke Kofoed
Author-email: hanniballykkekofoed@icloud.com
License: MIT
Keywords: python,math,mathematics
Classifier: License :: OSI Approved :: MIT License
Classifier: Programming Language :: Python :: 3
Classifier: Operating System :: OS Independent
License-File: LICENSE.txt
Requires-Dist: numpy
